WTG/__init__.py
WTG/module.py
WTG-0.1.1.dist-info/METADATA
WTG-0.1.1.dist-info/WHEEL
WTG-0.1.1.dist-info/top_level.txt
WTG-0.1.1.dist-info/RECORD
