Metadata-Version: 2.1
Name: WTG
Version: 0.1.1
Summary: This package can you help to move WEB to GUI
Home-page: 
Author: Amfetaminchik
Author-email: sponge-bob@krusty-krab.ru
Classifier: Programming Language :: Python :: 3
Classifier: License :: OSI Approved :: MIT License
Classifier: Operating System :: OS Independent
Requires-Dist: PyQt5
Requires-Dist: PyQtWebEngine
